pylinqext/__init__.py
pylinqext/__main__.py
pylinqext/cli.py
pylinqext/pylinqext.py
pylinqext-0.5.1.dist-info/LICENSE
pylinqext-0.5.1.dist-info/METADATA
pylinqext-0.5.1.dist-info/WHEEL
pylinqext-0.5.1.dist-info/top_level.txt
pylinqext-0.5.1.dist-info/RECORD
