Metadata-Version: 2.1
Name: pylinqext
Version: 0.5.1
Summary: for C#er, you can write code like LINQ.
Home-page: https://github.com/super-string
Download-URL: https://github.com/super-string
Author: super-string
Author-email: sh5937tech@gmail.com
License: MIT
License-File: LICENSE
